<?xml version="1.0" encoding="UTF-8"?>

<attribute>
	<health>100.0</health>
	<damage_melee_dices>2</damage_melee_dices>
	<damage_melee_sides>1</damage_melee_sides>
	<damage_ranged_dices>4</damage_ranged_dices>
	<damage_ranged_sides>4</damage_ranged_sides>
	<attackspeed_melee>0.5</attackspeed_melee>
	<attackspeed_ranged>2.0</attackspeed_ranged>
	<ranged_projectile>Fireball</ranged_projectile>
	<ability1>ArrowRain</ability1>
	<ability2>Charge</ability2>
	<ismelee>false</ismelee>
	<movementspeed>500</movementspeed>
</attribute>